nonebot_plugin_eve_tool/__init__.py
nonebot_plugin_eve_tool/_version.py
nonebot_plugin_eve_tool/api/__init__.py
nonebot_plugin_eve_tool/api/aioclient.py
nonebot_plugin_eve_tool/api/common.py
nonebot_plugin_eve_tool/api/dotlan.py
nonebot_plugin_eve_tool/api/esi/__init__.py
nonebot_plugin_eve_tool/api/esi/killmail.py
nonebot_plugin_eve_tool/api/esi/mail.py
nonebot_plugin_eve_tool/api/esi/market.py
nonebot_plugin_eve_tool/api/esi/universe.py
nonebot_plugin_eve_tool/api/janice.py
nonebot_plugin_eve_tool/api/other.py
nonebot_plugin_eve_tool/api/zkillboard.py
nonebot_plugin_eve_tool/command/__init__.py
nonebot_plugin_eve_tool/command/common.py
nonebot_plugin_eve_tool/command/contract.py
nonebot_plugin_eve_tool/command/help.py
nonebot_plugin_eve_tool/command/killmail.py
nonebot_plugin_eve_tool/command/link.py
nonebot_plugin_eve_tool/command/other.py
nonebot_plugin_eve_tool/command/price.py
nonebot_plugin_eve_tool/command/rank.py
nonebot_plugin_eve_tool/command/statis.py
nonebot_plugin_eve_tool/command/sub.py
nonebot_plugin_eve_tool/command/trans.py
nonebot_plugin_eve_tool/command/zkb.py
nonebot_plugin_eve_tool/database/__init__.py
nonebot_plugin_eve_tool/database/mysql/MysqlArray.py
nonebot_plugin_eve_tool/database/mysql/__init__.py
nonebot_plugin_eve_tool/database/mysql/search.py
nonebot_plugin_eve_tool/database/redis/RedisArray.py
nonebot_plugin_eve_tool/database/redis/__init__.py
nonebot_plugin_eve_tool/database/redis/cache.py
nonebot_plugin_eve_tool/database/redis/search.py
nonebot_plugin_eve_tool/model/__init__.py
nonebot_plugin_eve_tool/model/common.py
nonebot_plugin_eve_tool/model/config.py
nonebot_plugin_eve_tool/model/initialize/__init__.py
nonebot_plugin_eve_tool/model/initialize/market.py
nonebot_plugin_eve_tool/model/initialize/sde.py
nonebot_plugin_eve_tool/model/initialize/sql.py
nonebot_plugin_eve_tool/model/initialize/sub.py
nonebot_plugin_eve_tool/model/killmail.py
nonebot_plugin_eve_tool/model/sde.py
nonebot_plugin_eve_tool/src/__init__.py
nonebot_plugin_eve_tool-0.3.0.dist-info/LICENSE
nonebot_plugin_eve_tool-0.3.0.dist-info/METADATA
nonebot_plugin_eve_tool-0.3.0.dist-info/WHEEL
nonebot_plugin_eve_tool-0.3.0.dist-info/RECORD
