Metadata-Version: 2.1
Name: nonebot-plugin-eve-tool
Version: 0.3.0
Summary: A NoneBot based plugin provides information query services for EVE online.
License: GPL-3.0 license
Author: zifox666
Author-email: zifox666@gmail.com
Requires-Python: >=3.10,<4.0
Classifier: License :: Other/Proprietary License
Classifier: Programming Language :: Python :: 3
Classifier: Programming Language :: Python :: 3.10
Classifier: Programming Language :: Python :: 3.11
Classifier: Programming Language :: Python :: 3.12
Classifier: Programming Language :: Python :: 3.13
Requires-Dist: aiofiles (>=23.2.1,<24.0.0)
Requires-Dist: aiohttp (>=3.9.5,<4.0.0)
Requires-Dist: aiomysql (>=0.2.0,<0.3.0)
Requires-Dist: httpx (>=0.27.0,<0.28.0)
Requires-Dist: jieba (>=0.42.1,<0.43.0)
Requires-Dist: matplotlib (>=3.9.0,<4.0.0)
Requires-Dist: nonebot-plugin-alconna (>=0.47.1,<0.48.0)
Requires-Dist: nonebot-plugin-apscheduler (>=0.4.0,<0.5.0)
Requires-Dist: nonebot-plugin-htmlrender (>=0.3.2,<0.4.0)
Requires-Dist: nonebot-plugin-waiter (>=0.6.2,<0.7.0)
Requires-Dist: nonebot2 (>=2.3.1,<3.0.0)
Requires-Dist: nonebot_adapter_onebot (>=2.3.1,<3.0.0)
Requires-Dist: pillow (>=10.3.0,<11.0.0)
Requires-Dist: qrcode (>=7.4.2,<8.0.0)
Requires-Dist: redis (>=5.0.6,<6.0.0)
Requires-Dist: tqdm (>=4.66.4,<5.0.0)
Requires-Dist: urllib3 (>=2.2.3,<3.0.0)
Requires-Dist: websockets (>=12.0,<13.0)
Requires-Dist: yarl (>=1.9.4,<2.0.0)
Requires-Dist: zipp (>=3.19.2,<4.0.0)
